sddp/__init__.py
sddp/plugin.py
sddp-0.2.6.dist-info/METADATA
sddp-0.2.6.dist-info/WHEEL
sddp-0.2.6.dist-info/entry_points.txt
sddp-0.2.6.dist-info/top_level.txt
sddp-0.2.6.dist-info/RECORD
